sharecharts/__init__.py
sharecharts/utils.py
sharecharts/algo/__init__.py
sharecharts/algo/trend.py
sharecharts/chart/__init__.py
sharecharts/tushare/__init__.py
sharecharts/tushare/client.py
sharecharts/tushare/tushare_names.py
sharecharts-1.0.2.dist-info/METADATA
sharecharts-1.0.2.dist-info/WHEEL
sharecharts-1.0.2.dist-info/top_level.txt
sharecharts-1.0.2.dist-info/RECORD
