Metadata-Version: 2.1
Name: sharecharts
Version: 1.0.2
Summary: sharecharts
Home-page: UNKNOWN
Author: 
Author-email: yiliuyan161@126.com
Maintainer: yiliuyan
Maintainer-email: yiliuyan161@126.com
License: UNKNOWN
Platform: all
Classifier: Programming Language :: Python
Classifier: Operating System :: Microsoft :: Windows
Classifier: Operating System :: Unix
Classifier: Programming Language :: Python :: 3.7
Classifier: Programming Language :: Python :: 3.8
Classifier: Programming Language :: Python :: 3.9
Classifier: Programming Language :: Python :: 3.10
Requires-Dist: requests
Requires-Dist: numba
Requires-Dist: diskcache
Requires-Dist: pandas
Requires-Dist: numpy
Requires-Dist: chartspy
Requires-Dist: tqdm
Requires-Dist: akshare
Requires-Dist: simplejson
Requires-Dist: setuptools
